Workbook

Sheet Executive Summary
A2: AURA | Connector priorities
A5: Decision view | B5: 30 connectors • checked 2026-09-29
A7: Recommended first wave | B7: Microsoft Graph/Entra, SAP S/4HANA, SuccessFactors and ServiceNow. Start SPL National Address as a parallel conditional pilot once product access is confirmed.
A8: Parallel foundation | B8: OAuth2/OIDC, mTLS as required, secrets, per-tenant permission model, audit, retries/reconciliation, rate limits, test harness and versioning.
A9: Saudi access track | B9: Start sponsor/eligibility and contract discovery now for Nafath, Qiwa, GOSI, Yaqeen, Muqeem and Etimad product selection. Build only after an approved contract and use case.
A10: Commercial focus | B10: Validate SAP pipeline and actual 35% progress. Narrow the first pack to an agreed PR/PO or invoice/status workflow and a customer sandbox.
A11: Largest evidence gap | B11: The 14 guides are project gateway baselines. Most Saudi endpoint paths, issued credentials and production rights cannot be verified on official public pages.
A12: Key decision | B12: Select first customer/tenant, employee journeys, whether AURA executes transactions or presents governed handoffs, and who owns payment/invoice obligations.
A15: Wave | B15: Meaning | C15: Release condition
A16: 1 - Build | B16: Documented interface; strong use case | C16: Customer tenant/API product entitlement and approved scenario
A17: 2 - Conditional | B17: Documented interface; narrower or higher effort | C17: Confirmed demand, account and test environment
A18: 3 - Demand led | B18: Documented but narrow | C18: Named customer and commercial case
A19: D - Discovery | B19: Exact route, identity or access rights unverified | C19: Provider-approved contract, owner, sandbox and use case
A22: Roadmap assumption | B22: Assessment
A23: S/4HANA first; 35% complete | B23: Commercial priority recognized; progress and pipeline are internal claims to validate.
A24: Saudi open API squad | B24: SPL product exists; Etimad product and ZATCA direct vs intermediary scope need specific onboarding.
A25: 6–12 / 4–10 / 3–9+ weeks | B25: Roadmap planning ranges; not independently validated delivery commitments.

Sheet Prioritized Connector Register
A1: Rank | B1: Connector | C1: Category | D1: Wave | E1: Priority Score /100 | F1: Access status | G1: Confidence | H1: Use case | I1: AURA value rationale | J1: Recommended integration / data flow | K1: Interface evidence | L1: Access model | M1: Difficulty | N1: Difficulty drivers | O1: Provider onboarding / commercial | P1: Legal / regulatory | Q1: Prerequisites / blockers | R1: Open questions | S1: Value 1–5 | T1: Reach 1–5 | U1: Fit 1–5 | V1: Ease 1–5 | W1: Readiness 1–5 | X1: Access 1–5 | Y1: Official evidence URL(s) | Z1: Detailed connector document
A2: 1 | B2: Microsoft 365 / Microsoft Graph + Entra | C2: Enterprise | D2: =IF(F2="Discovery required","D - Discovery",IF(E2>=80,"1 - Build",IF(E2>=60,"2 - Conditional","3 - Demand led"))) -> 1 - Build | E2: =ROUND((S2*'Scoring & Methodology'!$B$6+T2*'Scoring & Methodology'!$B$7+U2*'Scoring & Methodology'!$B$8+V2*'Scoring & Methodology'!$B$9+W2*'Scoring & Methodology'!$B$10+X2*'Scoring & Methodology'!$B$11)/5,0) -> 85 | F2: Build eligible | G2: High | H2: • Employee sign-in and directory profile • Mail, calendar, Teams and file actions in AURA | I2: Broad daily reach and reusable identity/collaboration layer | J2: • Use Entra OAuth2/OIDC for sign-in and Graph REST for selected actions • Choose delegated or app permissions per workflow • Use supported change notifications where needed | K2: Official Graph APIs documented | L2: • Customer Microsoft tenant and app registration • Application permissions need tenant admin consent | M2: Medium | N2: • Least-privilege scopes vary by action • Tenant governance, throttling and notification lifecycle add work | O2: • Register AURA in the customer tenant • Obtain consent for the selected Graph scopes; commercial terms depend on tenant licensing | P2: Not verified as a generic legal requirement | Q2: • Customer tenant/admin sponsor and permission matrix • Agree retention rules and initial mail, calendar or file journeys | R2: Which actions require delegated user context versus app-only? | S2: 4 | T2: 5 | U2: 5 | V2: 4 | W2: 3 | X2: 4 | Y2: https://learn.microsoft.com/en-us/graph/auth-v2-service?tabs=http | Z2: Open detailed assessment
A3: 2 | B3: SAP S/4HANA | C3: Enterprise | D3: =IF(F3="Discovery required","D - Discovery",IF(E3>=80,"1 - Build",IF(E3>=60,"2 - Conditional","3 - Demand led"))) -> 1 - Build | E3: =ROUND((S3*'Scoring & Methodology'!$B$6+T3*'Scoring & Methodology'!$B$7+U3*'Scoring & Methodology'!$B$8+V3*'Scoring & Methodology'!$B$9+W3*'Scoring & Methodology'!$B$10+X3*'Scoring & Methodology'!$B$11)/5,0) -> 84 | F3: Build eligible | G3: Medium | H3: • Create or track procurement requests and orders • Show invoice status, supplier data and selected approvals | I3: Live pipeline and core execution system; roadmap states first enterprise release | J3: • Start with selected OData APIs in the customer S/4 tenant • Use tenant communication and authorized business roles • Map request IDs and reconcile status by supported API/event | K3: Official OData API documented | L3: • Customer-controlled S/4 environment • Only users or integrations with the required business roles | M3: High | N3: • Edition and release change API behavior • Business-role mapping, testing and reconciliation are substantial | O3: • Provision a customer tenant or sandbox and API roles • Sign off the first procurement/invoice scenarios with the customer | P3: Not verified as a generic legal requirement | Q3: • Confirm S/4 edition, tenant and scoped roles • Select the first two workflows; verify roadmap progress and access | R3: Validate claimed 35% progress and customer sandboxes; which PR/PO/status actions are in scope? | S3: 5 | T3: 4 | U3: 5 | V3: 3 | W3: 3 | X3: 4 | Y3: https://help.sap.com/docs/SAP_S4HANA_ON-PREMISE/91af7f8d3acd47da90d33aaacfcd0d59/dad2402e2ff543e7971d788bf35b12c1.html | Z3: Open detailed assessment
A4: 3 | B4: SAP SuccessFactors | C4: Enterprise | D4: =IF(F4="Discovery required","D - Discovery",IF(E4>=80,"1 - Build",IF(E4>=60,"2 - Conditional","3 - Demand led"))) -> 1 - Build | E4: =ROUND((S4*'Scoring & Methodology'!$B$6+T4*'Scoring & Methodology'!$B$7+U4*'Scoring & Methodology'!$B$8+V4*'Scoring & Methodology'!$B$9+W4*'Scoring & Methodology'!$B$10+X4*'Scoring & Methodology'!$B$11)/5,0) -> 84 | F4: Build eligible | G4: High | H4: • Show employee and organization information • Track leave and HR request status where modules support it | I4: Primary HR source for SAP customers | J4: • Use supported OData entities with OAuth2 API client • Sync only approved HR fields; use delta/event capability if enabled • Map external employee IDs and request outcomes | K4: Official OData API documented | L4: • Customer SuccessFactors test/production tenant • API access and role-based permissions set by customer | M4: Medium | N4: • Sensitive HR data needs narrow field scope • Entity permissions, pagination and tenant-specific schema vary | O4: • Register API client in the customer tenant • Grant OData and role-based permissions for selected entities | P4: Not verified as a generic legal requirement | Q4: • Test tenant and HR data owner • Confirm licensed modules, field map and leave actions | R4: Which Employee Central modules and leave transactions are licensed? | S4: 5 | T4: 4 | U4: 5 | V4: 3 | W4: 3 | X4: 4 | Y4: https://help.sap.com/docs/successfactors-platform/sap-successfactors-api-reference-guide-odata-v2/list-of-sap-successfactors-api-servers
A5: 4 | B5: ServiceNow | C5: Enterprise | D5: =IF(F5="Discovery required","D - Discovery",IF(E5>=80,"1 - Build",IF(E5>=60,"2 - Conditional","3 - Demand led"))) -> 1 - Build | E5: =ROUND((S5*'Scoring & Methodology'!$B$6+T5*'Scoring & Methodology'!$B$7+U5*'Scoring & Methodology'!$B$8+V5*'Scoring & Methodology'!$B$9+W5*'Scoring & Methodology'!$B$10+X5*'Scoring & Methodology'!$B$11)/5,0) -> 82 | F5: Build eligible | G5: High | H5: • Submit employee IT incidents or service requests • Display approval and ticket status in AURA | I5: Strong employee service desk execution and ticket transparency | J5: • Use approved Service Catalog/Table REST resources • Authenticate with configured OAuth/API identity and ACLs • Map ticket IDs and update status through events or polling | K5: Official REST Table API documented | L5: • Customer ServiceNow instance • API identity needs table/catalog ACLs | M5: Medium | N5: • Catalog items and fields vary by customer • ACLs and two-way status mapping require testing | O5: • Obtain a nonproduction customer instance • Set API identity/OAuth and catalog permissions | P5: Not verified as a generic legal requirement | Q5: • Choose exact catalog items and request owner • Agree approval transitions and status mapping | R5: Which catalog items and approval transitions are allowed? | S5: 4 | T5: 4 | U5: 5 | V5: 4 | W5: 3 | X5: 4 | Y5: https://www.servicenow.com/docs/r/zurich/api-reference/rest-apis/c_TableAPI.html
A6: 5 | B6: SPL National Address | C6: Saudi | D6: =IF(F6="Discovery required","D - Discovery",IF(E6>=80,"1 - Build",IF(E6>=60,"2 - Conditional","3 - Demand led"))) -> 2 - Conditional | E6: =ROUND((S6*'Scoring & Methodology'!$B$6+T6*'Scoring & Methodology'!$B$7+U6*'Scoring & Methodology'!$B$8+V6*'Scoring & Methodology'!$B$9+W6*'Scoring & Methodology'!$B$10+X6*'Scoring & Methodology'!$B$11)/5,0) -> 75 | F6: Build eligible | G6: Medium | H6: • Validate employee or office national address • Use verified address data for onboarding/service delivery | I6: Saudi-local onboarding quality with broad reach | J6: • Subscribe to the applicable SPL API product • Call approved address verification/retrieval operation • Store or cache results only under product terms | K6: Official National Address API advertised | L6: • Developer/business registration is available • Specific API product and production entitlement need confirmation | M6: Medium | N6: • Address matching and incomplete input need handling • Subscription terms, personal data and test cases add work | O6: • Create SPL developer/business account • Confirm relevant product subscription and production terms | P6: Not verified; confirm data handling with SPL/customer | Q6: • Obtain sample requests/responses and credentials • Confirm individual-address use and allowed data retention | R6: Does AURA qualify for individual address lookup and production use? | S6: 4 | T6: 5 | U6: 4 | V6: 3 | W6: 3 | X6: 3 | Y6: https://splonline.com.sa/en/national-address-api/ | Z6: Open detailed assessment
A7: 6 | B7: Oracle Fusion ERP / HCM | C7: Enterprise | D7: =IF(F7="Discovery required","D - Discovery",IF(E7>=80,"1 - Build",IF(E7>=60,"2 - Conditional","3 - Demand led"))) -> 2 - Conditional | E7: =ROUND((S7*'Scoring & Methodology'!$B$6+T7*'Scoring & Methodology'!$B$7+U7*'Scoring & Methodology'!$B$8+V7*'Scoring & Methodology'!$B$9+W7*'Scoring & Methodology'!$B$10+X7*'Scoring & Methodology'!$B$11)/5,0) -> 72 | F7: Build eligible | G7: High | H7: • Read worker and leave information • Create or track procurement requisitions | I7: Large-enterprise alternative to SAP | J7: • Use selected Fusion HCM/Procurement REST resources • Follow the customer environment’s approved authentication policy • Map request IDs and poll or use approved events for status | K7: Official REST resources documented | L7: • Customer Fusion environment and module access • Roles restrict HCM and procurement resources | M7: High | N7: • Security roles and modules differ by customer • Large payloads and environment access complicate testing | O7: • Obtain customer tenant and required module licenses • Provision REST roles and a test environment | P7: Not verified as a generic legal requirement | Q7: • Select one HCM and one ERP workflow • Confirm sandbox, roles, field map and data owner | R7: Which modules and customer security policy are present? | S7: 4 | T7: 4 | U7: 4 | V7: 2 | W7: 3 | X7: 4 | Y7: https://docs.oracle.com/en/cloud/saas/human-resources/farws/index.html | https://docs.oracle.com/en/cloud/saas/procurement/26c/fapra/api-purchase-requisitions.html
A8: 7 | B8: Dynamics 365 / Dataverse | C8: Enterprise | D8: =IF(F8="Discovery required","D - Discovery",IF(E8>=80,"1 - Build",IF(E8>=60,"2 - Conditional","3 - Demand led"))) -> 2 - Conditional | E8: =ROUND((S8*'Scoring & Methodology'!$B$6+T8*'Scoring & Methodology'!$B$7+U8*'Scoring & Methodology'!$B$8+V8*'Scoring & Methodology'!$B$9+W8*'Scoring & Methodology'!$B$10+X8*'Scoring & Methodology'!$B$11)/5,0) -> 70 | F8: Build eligible | G8: High | H8: • Create or view customer/employee service cases • Show case progress in AURA | I8: Reusable Microsoft ecosystem extension | J8: • Use Dataverse Web API with Entra OAuth • Choose app user or delegated access and table security roles • Use configured change tracking/events for updates | K8: Official Web API documented | L8: • Customer Dataverse environment • Licensed app/tables and security roles control access | M8: Medium | N8: • Custom tables and business rules differ by tenant • Application-user roles and governance need review | O8: • Register the app and environment application user • Grant only the required table/security roles | P8: Not verified as a generic legal requirement | Q8: • Identify the Dynamics workload and target tables • Obtain customer tenant and test records | R8: Which Dynamics app and tables hold employee requests? | S8: 3 | T8: 3 | U8: 4 | V8: 4 | W8: 3 | X8: 4 | Y8: https://learn.microsoft.com/en-us/power-apps/developer/data-platform/webapi/overview
A9: 8 | B9: PayTabs | C9: Saudi | D9: =IF(F9="Discovery required","D - Discovery",IF(E9>=80,"1 - Build",IF(E9>=60,"2 - Conditional","3 - Demand led"))) -> 2 - Conditional | E9: =ROUND((S9*'Scoring & Methodology'!$B$6+T9*'Scoring & Methodology'!$B$7+U9*'Scoring & Methodology'!$B$8+V9*'Scoring & Methodology'!$B$9+W9*'Scoring & Methodology'!$B$10+X9*'Scoring & Methodology'!$B$11)/5,0) -> 63 | F9: Build eligible | G9: High | H9: • Collect a fee for an eligible employee service • Reconcile payment before fulfilling the request | I9: Monetization only where AURA owns a payable journey | J9: • Create hosted payment request server-side and redirect user • Verify callback through server query before marking paid • Reconcile timeout, refund and duplicate states | K9: Official PayTabs integration documentation | L9: • Merchant account and commercial onboarding • Server credentials stay with the merchant backend | M9: Medium | N9: • Payment state and callback validation are sensitive • Refunds, reconciliation and ambiguous outcomes need testing | O9: • Sign merchant agreement and obtain profile/server key • Configure sandbox and approved callback URL | P9: Not verified; payment obligations require specific jurisdictional review | Q9: • Name merchant of record and paid service • Assign finance owner and settlement process | R9: Who is merchant of record, and which employee services are paid? | S9: 3 | T9: 3 | U9: 3 | V9: 3 | W9: 3 | X9: 4 | Y9: https://docs.paytabs.com/manuals/PT-API-Endpoints/Integration-Types-Manuals/Hosted-Payment-Page/HPP-Landing-Page/
A10: 9 | B10: IATA | C10: Saudi | D10: =IF(F10="Discovery required","D - Discovery",IF(E10>=80,"1 - Build",IF(E10>=60,"2 - Conditional","3 - Demand led"))) -> 3 - Demand led | E10: =ROUND((S10*'Scoring & Methodology'!$B$6+T10*'Scoring & Methodology'!$B$7+U10*'Scoring & Methodology'!$B$8+V10*'Scoring & Methodology'!$B$9+W10*'Scoring & Methodology'!$B$10+X10*'Scoring & Methodology'!$B$11)/5,0) -> 45 | F10: Build eligible | G10: Medium | H10: • Validate a travel agency code during vendor onboarding • Record valid/invalid result and freshness | I10: Useful for a narrow travel partner workflow | J10: • Use licensed CheckACode Web Service under IATA contract • Confirm the attached /checkacode route and headers with vendor • Match response by code and retain freshness metadata | K10: Official commercial CheckACode API product | L10: • Commercial IATA product/subscription • Exact attached gateway credential route is not publicly verified | M10: Medium | N10: • Product entitlement and response freshness need agreement • Attached credential format and batch behavior need testing | O10: • Confirm product eligibility and purchase terms • Obtain licensed API contract and test credentials | P10: Not verified | Q10: • Confirm travel-agency validation is needed • Approve budget, contract and permitted code use | R10: Is AURA a licensed subscriber, and is the gateway route IATA direct? | S10: 2 | T10: 1 | U10: 2 | V10: 3 | W10: 3 | X10: 3 | Y10: https://www.iata.org/en/services/data/travel-agent/global-data-products/checkacode-webservice/
A11: 10 | B11: Nafath | C11: Saudi | D11: =IF(F11="Discovery required","D - Discovery",IF(E11>=80,"1 - Build",IF(E11>=60,"2 - Conditional","3 - Demand led"))) -> D - Discovery | E11: =ROUND((S11*'Scoring & Methodology'!$B$6+T11*'Scoring & Methodology'!$B$7+U11*'Scoring & Methodology'!$B$8+V11*'Scoring & Methodology'!$B$9+W11*'Scoring & Methodology'!$B$10+X11*'Scoring & Methodology'!$B$11)/5,0) -> 68 | F11: Discovery required | G11: Low | H11: • Verify national digital identity for an employee journey • Potentially support trusted sign-in or approval | I11: High potential trust and reach | J11: • Proposed: integrate only through an approved identity flow • Request provider contract before selecting endpoints/auth • Use governed handoff while access is unresolved | K11: Official national SSO service; AURA API contract unverified | L11: • Government-approved relying-party route not established for AURA • No public AURA-ready endpoint confirmed | M11: High | N11: • Identity assurance and security testing are demanding • External eligibility and approval are the main gate | O11: • Identify provider sponsor and relying-party eligibility • Confirm onboarding process and entitlement; terms not verified | P11: Not verified | Q11: • Confirm AURA/customer eligibility and use case • Obtain approved test environment and technical contract | R11: Can AURA qualify directly or through a licensed integrator? | S11: 5 | T11: 5 | U11: 5 | V11: 1 | W11: 1 | X11: 1 | Y11: https://my.gov.sa/en/services/119727
A12: 11 | B12: Qiwa | C12: Saudi | D12: =IF(F12="Discovery required","D - Discovery",IF(E12>=80,"1 - Build",IF(E12>=60,"2 - Conditional","3 - Demand led"))) -> D - Discovery | E12: =ROUND((S12*'Scoring & Methodology'!$B$6+T12*'Scoring & Methodology'!$B$7+U12*'Scoring & Methodology'!$B$8+V12*'Scoring & Methodology'!$B$9+W12*'Scoring & Methodology'!$B$10+X12*'Scoring & Methodology'!$B$11)/5,0) -> 65 | F12: Discovery required | G12: Low | H12: • Show employment-contract or job-change status • Guide employee through selected labor service | I12: Major Saudi employee lifecycle value | J12: • Proposed: use partner/customer route only after API rights are confirmed • Otherwise direct user to the official workflow • Do not assume a public execution API | K12: Official service portal; external API unverified | L12: • Qiwa portal services are documented • External API and AURA access rights remain unverified | M12: High | N12: • Employment data and process rules are sensitive • Provider entitlement is unresolved | O12: • Find employer sponsor and chosen Qiwa service • Seek provider agreement and machine-access terms | P12: Not verified | Q12: • Choose exact contract/job-change action • Confirm customer authority and supported interface | R12: Is there a supported external interface for the chosen service? | S12: 5 | T12: 4 | U12: 5 | V12: 1 | W12: 1 | X12: 1 | Y12: https://qiwa.sa/en/services
A13: 12 | B13: Etimad APIs | C13: Saudi | D13: =IF(F13="Discovery required","D - Discovery",IF(E13>=80,"1 - Build",IF(E13>=60,"2 - Conditional","3 - Demand led"))) -> D - Discovery | E13: =ROUND((S13*'Scoring & Methodology'!$B$6+T13*'Scoring & Methodology'!$B$7+U13*'Scoring & Methodology'!$B$8+V13*'Scoring & Methodology'!$B$9+W13*'Scoring & Methodology'!$B$10+X13*'Scoring & Methodology'!$B$11)/5,0) -> 64 | F13: Discovery required | G13: Medium | H13: • Show public-sector procurement information • Track a selected government purchase request | I13: Strategic for Saudi government customers | J13: • Register in Etimad developer portal • Subscribe to the exact approved API product • Implement its published contract after catalog/sandbox review | K13: Official developer portal; exact product not selected | L13: • Portal serves eligible beneficiary groups • Entitlement is specific to each API product | M13: Medium | N13: • Available product may not match AURA’s request • Customer eligibility and production subscription need checking | O13: • Create portal account and select API product • Confirm customer eligibility and subscription approval | P13: Not verified | Q13: • Name the procurement workflow and API product • Get sandbox access and production-use terms | R13: Which Etimad APIs support AURA’s exact request and who is eligible? | S13: 4 | T13: 2 | U13: 4 | V13: 3 | W13: 2 | X13: 3 | Y13: https://apiportal.etimad.sa/en/get-started
A14: 13 | B14: Absher | C14: Saudi | D14: =IF(F14="Discovery required","D - Discovery",IF(E14>=80,"1 - Build",IF(E14>=60,"2 - Conditional","3 - Demand led"))) -> D - Discovery | E14: =ROUND((S14*'Scoring & Methodology'!$B$6+T14*'Scoring & Methodology'!$B$7+U14*'Scoring & Methodology'!$B$8+V14*'Scoring & Methodology'!$B$9+W14*'Scoring & Methodology'!$B$10+X14*'Scoring & Methodology'!$B$11)/5,0) -> 56 | F14: Discovery required | G14: Low | H14: • Guide employees to a government transaction • Show status only if an authorized route exists | I14: Broad recognition but direct execution rights uncertain | J14: • Prefer official employee handoff now • Proposed direct integration only after sanctioned contract and API spec • Keep transaction ownership with authorized party | K14: Official Absher Business portal; direct API unverified | L14: • Official business portal exists • Direct AURA API access is unverified | M14: High | N14: • Government transaction permissions are uncertain • Identity, authorization and transaction ownership add risk | O14: • Confirm whether approved provider route exists • Use handoff design if no sanctioned integration | P14: Not verified | Q14: • Select exact employee transaction • Verify enterprise eligibility and provider owner | R14: Does any direct API exist for AURA’s use case? | S14: 4 | T14: 4 | U14: 4 | V14: 1 | W14: 1 | X14: 1 | Y14: https://www.absher.sa/wps/portal/business/Home
A15: 14 | B15: GOSI | C15: Saudi | D15: =IF(F15="Discovery required","D - Discovery",IF(E15>=80,"1 - Build",IF(E15>=60,"2 - Conditional","3 - Demand led"))) -> D - Discovery | E15: =ROUND((S15*'Scoring & Methodology'!$B$6+T15*'Scoring & Methodology'!$B$7+U15*'Scoring & Methodology'!$B$8+V15*'Scoring & Methodology'!$B$9+W15*'Scoring & Methodology'!$B$10+X15*'Scoring & Methodology'!$B$11)/5,0) -> 56 | F15: Discovery required | G15: Low | H15: • Show social-insurance status when authorized • Support employer contribution visibility | I15: Useful for HR verification in Saudi employers | J15: • Proposed: use approved GOSI/customer contract if available • Request technical interface before implementation • Avoid assuming a generic public API | K15: Official e-services; external API unverified | L15: • Official e-services exist • External machine access for AURA is unverified | M15: High | N15: • Government data rights and identity controls are significant • Access route and test data are unresolved | O15: • Obtain employer authority and service scope • Confirm provider-approved route and sandbox | P15: Not verified | Q15: • Name data owner and permitted purpose • Secure gateway sponsor, contract and test environment | R15: Can employer obtain sanctioned machine access? | S15: 4 | T15: 4 | U15: 4 | V15: 1 | W15: 1 | X15: 1 | Y15: https://www.gosi.gov.sa/GOSIOnline/Services&locale=en_US
A16: 15 | B16: Muqeem | C16: Saudi | D16: =IF(F16="Discovery required","D - Discovery",IF(E16>=80,"1 - Build",IF(E16>=60,"2 - Conditional","3 - Demand led"))) -> D - Discovery | E16: =ROUND((S16*'Scoring & Methodology'!$B$6+T16*'Scoring & Methodology'!$B$7+U16*'Scoring & Methodology'!$B$8+V16*'Scoring & Methodology'!$B$9+W16*'Scoring & Methodology'!$B$10+X16*'Scoring & Methodology'!$B$11)/5,0) -> 53 | F16: Discovery required | G16: Low | H16: • Track expatriate residency or visa services • Present employee status or official handoff | I16: Relevant to Saudi employer mobility workflows | J16: • Proposed: use customer-authorized Muqeem contract if offered • Otherwise provide governed employee handoff • Do not infer API operations | K16: Service product context; external API unverified | L16: • Commercial customer/provider rights may be required • External AURA API entitlement unverified | M16: High | N16: • Immigration data requires careful authorization • Provider approval and transaction rules are unknown | O16: • Confirm employer subscription and partner eligibility • Obtain provider agreement for selected transaction | P16: Not verified | Q16: • Specify residency/visa transaction • Confirm authorized tenant and access contract | R16: Is API access offered to AURA for this transaction? | S16: 4 | T16: 3 | U16: 4 | V16: 1 | W16: 1 | X16: 1 | Y16: https://elm.sa/en/our-business/digital-products/Pages/security-products.aspx
A17: 16 | B17: Yaqeen | C17: Saudi | D17: =IF(F17="Discovery required","D - Discovery",IF(E17>=80,"1 - Build",IF(E17>=60,"2 - Conditional","3 - Demand led"))) -> D - Discovery | E17: =ROUND((S17*'Scoring & Methodology'!$B$6+T17*'Scoring & Methodology'!$B$7+U17*'Scoring & Methodology'!$B$8+V17*'Scoring & Methodology'!$B$9+W17*'Scoring & Methodology'!$B$10+X17*'Scoring & Methodology'!$B$11)/5,0) -> 53 | F17: Discovery required | G17: Low | H17: • Verify selected employee/beneficiary identity fields • Improve onboarding data quality | I17: Improves data quality and fraud controls for eligible workflows | J17: • Proposed: use an Elm-approved product/partner route • Obtain exact API contract and purpose limits first • Send only approved verification fields | K17: Elm verification service context; exact API unverified | L17: • Commercial/provider-approved access • AURA’s exact API and permitted purpose are unverified | M17: High | N17: • Identity data is sensitive • Eligibility, allowed fields and credential rules need confirmation | O17: • Discuss agreement and intended purpose with Elm • Request test credentials and commercial terms | P17: Not verified | Q17: • Define identity-check decision and legal purpose • Confirm eligible customer and provider entitlement | R17: What fields and verification purpose are permitted? | S17: 4 | T17: 3 | U17: 4 | V17: 1 | W17: 1 | X17: 1 | Y17: https://elm.sa/en/our-business/digital-products/Pages/security-products.aspx
A18: 17 | B18: ZATCA Integration Service | C18: Saudi | D18: =IF(F18="Discovery required","D - Discovery",IF(E18>=80,"1 - Build",IF(E18>=60,"2 - Conditional","3 - Demand led"))) -> D - Discovery | E18: =ROUND((S18*'Scoring & Methodology'!$B$6+T18*'Scoring & Methodology'!$B$7+U18*'Scoring & Methodology'!$B$8+V18*'Scoring & Methodology'!$B$9+W18*'Scoring & Methodology'!$B$10+X18*'Scoring & Methodology'!$B$11)/5,0) -> 49 | F18: Discovery required | G18: Medium | H18: • Issue an invoice for a paid employee service • Retrieve invoice status or file for finance | I18: Useful finance workflow only when AURA bills locally | J18: • Attached /billing/v3 is an intermediary contract, not direct ZATCA • Direct Fatoora route needs its own EGS specification/onboarding • Reconcile accepted invoice IDs and unknown outcomes | K18: Official Fatoora program; attached intermediary contract unverified externally | L18: • Direct route requires applicable taxpayer/solution onboarding • Intermediary route requires separate gateway agreement | M18: High | N18: • Tax profile, signing/compliance and reconciliation are complex • Gateway rights and exact route must be separated | O18: • Direct: complete applicable Fatoora EGS onboarding • Intermediary: obtain owner-issued credentials and contract | P18: ZATCA e-invoicing rules only if in-scope taxpayer; applicability to AURA Not verified | Q18: • Confirm invoicing entity, VAT applicability and billing owner • Choose direct or intermediary route and test in sandbox | R18: Does AURA issue tax invoices? Who owns intermediary contract and credentials? | S18: 3 | T18: 2 | U18: 3 | V18: 2 | W18: 2 | X18: 2 | Y18: https://zatca.gov.sa/en/E-Invoicing/SystemsDevelopers/Pages/default.aspx
... A31: 30 | B31: Kidana | C31: Saudi | D31: =IF(F31="Discovery required","D - Discovery",IF(E31>=80,"1 - Build",IF(E31>=60,"2 - Conditional","3 - Demand led"))) -> D - Discovery | E31: =ROUND((S31*'Scoring & Methodology'!$B$6+T31*'Scoring & Methodology'!$B$7+U31*'Scoring & Methodology'!$B$8+V31*'Scoring & Methodology'!$B$9+W31*'Scoring & Methodology'!$B$10+X31*'Scoring & Methodology'!$B$11)/5,0) -> 29 | F31: Discovery required | G31: Low | H31: • Retrieve a Hajj-site handover report file • Deliver it to an authorized employee | I31: Specialized Hajj operations | J31: • Project proposes GET handover file by reportId • Verify endpoint and authorization with Kidana/owner • Validate media type and access before storage | K31: Official organization context; handover API unverified | L31: • Partner/project access unknown • Public Kidana site does not verify file API | M31: High | N31: • File authorization and size/format checks • Program-specific report entitlement is unclear | O31: • Secure Kidana project sponsorship • Confirm report ID scope and authorization contract | P31: Not verified | Q31: • Identify Hajj operator and file owner • Confirm permitted storage and test report IDs | R31: Who owns report IDs and may AURA store files? | S31: 2 | T31: 1 | U31: 2 | V31: 1 | W31: 1 | X31: 1 | Y31: https://kidana.com.sa/

Sheet Scoring & Methodology
A2: Scoring & methodology
A5: Criterion | B5: Weight | C5: Scale (1 → 5) | D5: Evidence and interpretation
A6: AURA use-case value | B6: 25 | C6: 1 marginal; 3 useful; 5 core request execution | D6: Pipeline value considered here; roadmap claim noted where not independently verified
A7: Employee reach | B7: 15 | C7: 1 niche sector; 3 subset; 5 broad daily use | D7: Reach is expected AURA adoption, not provider market share
A8: Strategic fit | B8: 20 | C8: 1 peripheral; 3 adjacent; 5 core hub/enterprise system | D8: Direct relevance to employee hub and reusable architecture
A9: Implementation ease | B9: 15 | C9: 1 very hard/unknown; 3 medium; 5 low effort | D9: Inverse of difficulty; includes testing, operations and data complexity
A10: Dependency readiness | B10: 10 | C10: 1 missing sponsor/spec; 3 potential tenant; 5 ready sandbox | D10: Roadmap planning claim alone does not prove a live sandbox
A11: Access feasibility | B11: 15 | C11: 1 rights unavailable/unverified; 3 enrollment/contract; 5 self-service | D11: Public docs do not imply AURA has production entitlement
A14: Formula / rule | B14: Definition
A15: Priority score | B15: ROUND(weighted sum of the six 1–5 ratings / 5, 0). The six weights sum to 100. This is the only numeric priority score.
A16: Access status | B16: Build eligible when the documented interface and access route can be pursued with customer/provider onboarding; otherwise Discovery required.
A17: Ranking | B17: Build eligible connectors first, ordered by descending Priority Score; then Discovery required connectors ordered by score. Rank is a snapshot; sort again after changing inputs.
A18: Wave 1 | B18: Build eligible with Priority Score ≥80. Customer tenant/product entitlement and scenario sign-off remain release prerequisites.
A19: Wave 2 / 3 | B19: Build eligible with Priority Score 60–79 / <60, respectively.
A20: Discovery gate | B20: Exact provider identity, supported interface or AURA integration rights unverified: D regardless of score. Start access discovery in parallel with build waves.
A23: Evidence rule | B23: Use official pages to confirm provider interface and access; project guides are proposed/owner baselines, not proof of AURA entitlement.
A24: Permissions | B24: Provider onboarding and commercial agreement separated from law. Legal field says Not verified unless an applicable official requirement is established.
A25: Difficulty | B25: Unknown when provider identity/access makes engineering assessment unreliable; otherwise includes integration, testing and operations.
A26: Direct route | B26: Direct is an approach under each provider, never a separate connector row.
A27: Scope | B27: Exactly 24 named Saudi services and 6 enterprise systems. Composite names retained as requested.
A28: Checked | B28: 2026-09-29

Sheet Sources & Discrepancies
A2: Sources & discrepancies
A5: Source ID | B5: Connector / claim | C5: Source type | D5: Official URL / project file | E5: Checked | F5: Supports | G5: Conflict or unresolved point
A6: R0 | B6: Roadmap priority and parallel squads | C6: Project roadmap | D6: AURA_Component_Roadmap_Interactive_v2.html, Enterprise & Saudi Connectors | E6: 2026-09-29 | F6: S/4 priority #1; 35% claim; squads, estimates and dependencies | G6: 35%, pipeline, timeboxes and Saudi quick-win access are internal claims; confirm with owners.
A7: GRAPH | B7: Microsoft 365 / Microsoft Graph + Entra | C7: Official provider | D7: https://learn.microsoft.com/en-us/graph/auth-v2-service?tabs=http | E7: 2026-09-29 | F7: Application permissions and admin consent for Graph | G7: Roadmap says 4–8 weeks; effort depends on exact scopes and tenants.
A8: S4 | B8: SAP S/4HANA | C8: Official provider | D8: https://help.sap.com/docs/SAP_S4HANA_ON-PREMISE/91af7f8d3acd47da90d33aaacfcd0d59/dad2402e2ff543e7971d788bf35b12c1.html | E8: 2026-09-29 | F8: Purchase requisition OData V4; authorized roles required | G8: Roadmap 35% and 8–12 week estimate are internal assertions, not independently verified.
A9: SF | B9: SAP SuccessFactors | C9: Official provider | D9: https://help.sap.com/docs/successfactors-platform/sap-successfactors-api-reference-guide-odata-v2/list-of-sap-successfactors-api-servers | E9: 2026-09-29 | F9: SuccessFactors OData API servers documented | G9: Roadmap 6–10 week estimate not independently validated.
A10: SN | B10: ServiceNow | C10: Official provider | D10: https://www.servicenow.com/docs/r/zurich/api-reference/rest-apis/c_TableAPI.html | E10: 2026-09-29 | F10: ServiceNow Table API documented | G10: Roadmap timing is planning estimate.
A11: SPL | B11: SPL National Address | C11: Official provider | D11: https://splonline.com.sa/en/national-address-api/ | E11: 2026-09-29 | F11: National Address API offered; registration/product access to confirm | G11: Roadmap calls this an open quick win; exact product access and production terms still need confirmation.
A12: ORACLE | B12: Oracle Fusion ERP / HCM | C12: Official provider | D12: https://docs.oracle.com/en/cloud/saas/human-resources/farws/index.html | E12: 2026-09-29 | F12: Fusion HCM REST API documented | G12: Roadmap 8–12 weeks assumes accessible tenant and narrow pack.
A13: ORACLEPR | B13: Oracle Fusion ERP / HCM | C13: Official provider | D13: https://docs.oracle.com/en/cloud/saas/procurement/26c/fapra/api-purchase-requisitions.html | E13: 2026-09-29 | F13: Procurement requisition REST resource | G13: Roadmap 8–12 weeks assumes accessible tenant and narrow pack.
A14: DV | B14: Dynamics 365 / Dataverse | C14: Official provider | D14: https://learn.microsoft.com/en-us/power-apps/developer/data-platform/webapi/overview | E14: 2026-09-29 | F14: Dataverse Web API documented | G14: Roadmap groups this with ServiceNow; use case depends on tenant.
A15: PAY | B15: PayTabs | C15: Official provider | D15: https://docs.paytabs.com/manuals/PT-API-Endpoints/Integration-Types-Manuals/Hosted-Payment-Page/HPP-Landing-Page/ | E15: 2026-09-29 | F15: Hosted payment API integration documentation | G15: Project guide /request and /query align conceptually; exact fields/region endpoints need merchant docs.
A16: P-02 | B16: PayTabs | C16: Project guide | D16: 02-02-paytabs.docx | E16: 2026-09-29 | F16: Gateway route/auth/payload proposal; not proof of production access | G16: Project guide /request and /query align conceptually; exact fields/region endpoints need merchant docs.
... A51: P-12 | B51: Kidana | C51: Project guide | D51: 12-12-kidana.docx | E51: 2026-09-29 | F51: Gateway route/auth/payload proposal; not proof of production access | G51: Public provider page does not verify handover endpoint.
